cdk_ec2_key_pair/__init__.py
cdk_ec2_key_pair/py.typed
cdk_ec2_key_pair/_jsii/__init__.py
cdk_ec2_key_pair/_jsii/cdk-ec2-key-pair@5.0.0.jsii.tgz
cdk_ec2_key_pair-5.0.0.dist-info/LICENSE
cdk_ec2_key_pair-5.0.0.dist-info/METADATA
cdk_ec2_key_pair-5.0.0.dist-info/WHEEL
cdk_ec2_key_pair-5.0.0.dist-info/top_level.txt
cdk_ec2_key_pair-5.0.0.dist-info/RECORD
