Metadata-Version: 2.1
Name: cdk-ec2-key-pair
Version: 5.0.0
Summary: CDK Construct for managing EC2 key pairs
Home-page: https://github.com/udondan/cdk-ec2-key-pair
Author: Daniel Schroeder
License: Apache-2.0
Project-URL: Source, https://github.com/udondan/cdk-ec2-key-pair.git
Classifier: Intended Audience :: Developers
Classifier: Operating System :: OS Independent
Classifier: Programming Language :: JavaScript
Classifier: Programming Language :: Python :: 3 :: Only
Classifier: Programming Language :: Python :: 3.9
Classifier: Programming Language :: Python :: 3.10
Classifier: Programming Language :: Python :: 3.11
Classifier: Typing :: Typed
Classifier: Development Status :: 5 - Production/Stable
Classifier: License :: OSI Approved
Requires-Python: ~=3.9
License-File: LICENSE
Requires-Dist: aws-cdk-lib <3.0.0,>=2.219.0
Requires-Dist: constructs <11.0.0,>=10.0.0
Requires-Dist: jsii <2.0.0,>=1.117.0
Requires-Dist: publication >=0.0.3
Requires-Dist: typeguard <4.3.0,>=2.13.3
